AUTHORS
ChangeLog
LICENSE
README.rst
marke37.sublime-project
setup.cfg
setup.py
docs/Makefile
docs/codigo_linea.rst
docs/conf.py
docs/convertidor.rst
docs/directiva_sphinx.rst
docs/editor_en_linea.rst
docs/errores.rst
docs/especificación.rst
docs/index.rst
docs/make.bat
docs/plantilla_html.rst
docs/pygments.rst
docs/sublime.rst
marke37/__init__.py
marke37/convertidor_marke37.py
marke37/letra.py
marke37/letra_im.py
marke37/letra_im_html.py
marke37/letra_latex.py
marke37/letra_md.py
marke37/linea.py
marke37/marke37.py
marke37/seccion.py
marke37/simbolos.py
marke37.egg-info/PKG-INFO
marke37.egg-info/SOURCES.txt
marke37.egg-info/dependency_links.txt
marke37.egg-info/entry_points.txt
marke37.egg-info/not-zip-safe
marke37.egg-info/pbr.json
marke37.egg-info/top_level.txt
marke37/plantillas/html/bulma.html
marke37/test/__init__.py
marke37/test/run_tests.py
marke37/test/test_letra.py
marke37/test/test_letra_base.py
marke37/test/test_letra_im.py
marke37/test/test_letra_latex.py
marke37/test/test_letra_md.py
marke37/test/test_linea.py
marke37/test/test_seccion.py
marke37/test/archivos/letra_completa.me37
marke37/test/archivos/solo_versos.me37
marke37/test/archivos/titulo.me37
marke37/test/archivos/titulo_coro_precoro_postcoro.me37
marke37/test/archivos/titulo_desfasado.me37
marke37/test/archivos/titulo_intro_verso.me37
marke37/test/archivos/titulo_intro_verso_outro.me37
marke37/test/archivos/titulo_verso_coro_y_puente.me37
marke37/test/archivos/titulo_verso_y_coro.me37
marke37/test/archivos/titulo_y_dos_versos.me37
marke37/test/archivos/titulo_y_dos_versos_lineas_vacias.me37
marke37/test/archivos/titulo_y_verso.me37